boston_logger/__init__.py
boston_logger/config.py
boston_logger/context_managers.py
boston_logger/logger.py
boston_logger/middleware.py
boston_logger/requests_monkey_patch.py
boston_logger/sensitive_paths.py
boston_logger-1.3.0.dist-info/LICENSE
boston_logger-1.3.0.dist-info/METADATA
boston_logger-1.3.0.dist-info/WHEEL
boston_logger-1.3.0.dist-info/top_level.txt
boston_logger-1.3.0.dist-info/RECORD
