Metadata-Version: 2.1
Name: boston-logger
Version: 1.3.0
Author: Aaron McMillin
Author-email: AMcMillin@jbssolutions.com
Project-URL: Source, https://github.com/JBSinc/boston-logger
Classifier: Development Status :: 5 - Production/Stable
Classifier: Intended Audience :: Developers
Classifier: Topic :: System :: Logging
Classifier: License :: OSI Approved :: ISC License (ISCL)
Classifier: Programming Language :: Python :: 3
Classifier: Programming Language :: Python :: 3.8
Classifier: Programming Language :: Python :: 3.9
Classifier: Programming Language :: Python :: 3.10
Classifier: Programming Language :: Python :: 3 :: Only
Requires-Python: >=3.7, <4
License-File: LICENSE
Requires-Dist: requests (>=2.18.0)
Requires-Dist: configular (>=1.1.0)
Provides-Extra: django
Requires-Dist: Django (>=1.10) ; extra == 'django'
Provides-Extra: test
Requires-Dist: pytest ; extra == 'test'
Requires-Dist: pytest-coverage ; extra == 'test'
Requires-Dist: pytest-mock ; extra == 'test'
Requires-Dist: python-dateutil ; extra == 'test'
Requires-Dist: Django (<5,>=2.2) ; extra == 'test'
